[1,["ecpdLyjvZBwrvm+cedCcQy","1cgWaFj3xCnr+HPEkJe6YA","ceoLy2U4JIA7hbfMivTsjg","18BoBpmLpIa7g5MsF2MetT","0c4tS2IE9DuaMK/B7V+7sE","03pmM3TJJMzJJ1MH8LK0wA","a2MjXRFdtLlYQ5ouAFv/+R","f1TLhO8t5Cp5obaDP5c97Y","e5ta4mzdxOfY6hCABgiXlc","83YG+mKF9FM5+Sa80ymkwP","333y5xM+5K0LBWGoG09amU"],["node","_spriteFrame","_N$target","_parent","_textureSetter","root","scrollView","cancelLabel","resetLabel","titelLabel","animation","data","showClip","hideClip"],[["cc.Node",["_name","_opacity","_components","_prefab","_contentSize","_parent","_children","_trs","_color"],1,9,4,5,1,2,7,5],["cc.Widget",["_alignFlags","_top","_originalWidth","_originalHeight","_left","_right","_bottom","node"],-4,1],["cc.Node",["_name","_prefab","_contentSize","_trs","_children","_components","_color","_anchorPoint","_parent"],2,4,5,7,2,12,5,5,1],["cc.Node",["_name","_parent","_components","_prefab","_contentSize","_trs","_children","_color","_anchorPoint"],2,1,2,4,5,7,2,5,5],["cc.Sprite",["_sizeMode","_type","_isTrimmedMode","node","_materials","_spriteFrame"],0,1,3,6],["cc.Label",["_string","_fontSize","_styleFlags","_N$verticalAlign","_lineHeight","_enableWrapText","_N$overflow","_N$horizontalAlign","node","_materials"],-5,1,3],["cc.PrefabInfo",["fileId","root","asset"],2,1,1],"cc.SpriteFrame",["cc.Prefab",["_name"],2],["2457arSHXNKiqefBy7sYbr9",["clickToback","coverBanner","node","animation","titelLabel","nameLabel","valuesLabel","resetLabel","cancelLabel","nameOneLabel","valuesOneLabel","nameThreeLabel","valuesThreeLabel","subTitleLabel","scrollView","showClip","hideClip"],1,1,1,1,2,2,1,1,2,2,2,2,2,1,6,6],["cc.BlockInputEvents",["node"],3,1],["cc.Layout",["_resize","_N$layoutType","node","_layoutSize"],1,1,5],["cc.Button",["_N$transition","node","clickEvents","_N$target"],2,1,9,1],["cc.ClickEvent",["_componentId","handler","target"],1,1],["cc.Mask",["_N$alphaThreshold","node","_materials"],2,1,3],["cc.ScrollView",["horizontal","bounceDuration","_N$horizontalScrollBar","_N$verticalScrollBar","node","_N$content"],-1,1,1],["cc.Animation",["node","_clips"],3,1,3]],[[6,0,1,2,2],[3,0,1,2,3,7,4,8,5,2],[2,0,8,4,1,2,3,2],[0,0,5,2,3,4,7,2],[5,0,1,4,5,2,3,6,8,9,8],[5,0,1,4,2,7,3,8,9,7],[4,3,4,5,1],[0,0,5,6,2,3,4,7,2],[4,1,0,3,4,5,3],[5,0,1,4,5,2,7,3,6,8,9,9],[1,0,4,5,1,6,7,6],[11,0,1,2,3,3],[12,0,1,2,3,2],[13,0,1,2,3],[5,0,1,5,2,3,6,8,9,7],[2,0,8,5,1,6,2,7,3,2],[3,0,1,2,3,4,5,2],[1,0,2,3,7,4],[1,0,1,7,3],[10,0,1],[8,0,2],[2,0,4,5,1,6,2,3,2],[2,0,4,1,2,7,3,2],[0,0,5,6,2,3,4,2],[0,0,6,2,3,4,2],[0,0,1,5,2,3,8,4,3],[0,0,5,2,3,4,2],[3,0,1,6,2,3,4,5,2],[3,0,1,2,3,4,2],[9,0,1,2,3,4,5,6,7,8,9,10,11,12,13,14,15,16,3],[1,0,4,5,1,2,7,6],[1,0,1,6,2,3,7,6],[6,1,2,1],[4,0,3,4,5,2],[4,0,2,3,4,5,3],[14,0,1,2,2],[15,0,1,2,3,4,5,5],[16,0,1,1]],[[[{"name":"popup_bg_clean","rect":[0,0,628,234],"offset":[0,0],"originalSize":[628,234],"capInsets":[40,108,40,50]}],[7],0,[0],[4],[5]],[[[20,"ReportWindow"],[21,"ReportWindow",[-62,-63],[[[29,true,true,-58,-57,-56,[-48,-49,-50,-51,-52,-53,-54,-55],[-40,-41,-42,-43,-44,-45,-46,-47],-39,-38,[-30,-31,-32,-33,-34,-35,-36,-37],[-22,-23,-24,-25,-26,-27,-28,-29],[-14,-15,-16,-17,-18,-19,-20,-21],[-6,-7,-8,-9,-10,-11,-12,-13],[-3,-4,-5],-2,115,116],-59,[17,45,100,100,-60],[19,-61]],4,1,4,4],[32,-1,0],[4,4278190080],[5,750,1334],[375,667,0,0,0,0,1,1,1,1]],[22,"content",[-64,-65,-66,-67,-68,-69,-70,-71,-72],[0,"39kkJv7TtNOKFCQz+Xa+qd",1,0],[5,600,2085],[0,0.5,1],[0,430,0,0,0,0,1,1,1,1]],[7,"content_total",2,[-75,-76,-77,-78,-79,-80,-81,-82],[[10,41,30,30,74.11300000000028,-374.1130000000003,-73],[11,1,2,-74,[5,540,600]]],[0,"49NitwTdlKmru7b6rqtvG+",1,0],[5,540,600],[0,-374.1130000000003,0,0,0,0,1,1,1,1]],[7,"content_cardone",2,[-85,-86,-87,-88,-89,-90,-91,-92],[[10,41,30,30,769.8879999999999,-1069.888,-83],[11,1,2,-84,[5,540,600]]],[0,"b9AstW1lNMeZgq6eVkQi3b",1,0],[5,540,600],[0,-1069.888,0,0,0,0,1,1,1,1]],[7,"content_cardthree",2,[-95,-96,-97,-98,-99,-100,-101,-102],[[10,41,30,30,1467,-1773.049,-93],[11,1,2,-94,[5,540,600]]],[0,"972vUZbyhLEJqwZDFswv1o",1,0],[5,540,600],[0,-1767,0,0,0,0,1,1,1,1]],[23,"bg",1,[-105,-106,-107,-108],[[8,1,0,-103,[111],112],[19,-104]],[0,"89qqKWjJNCU6UlN4Qt4hT7",1,0],[5,626,1144]],[7,"btn_blue",6,[-112],[[8,1,0,-109,[6],7],[12,1,-111,[[13,"2457arSHXNKiqefBy7sYbr9","onResetDataClick",1]],-110]],[0,"8b/sN9ujlBjpMmkPXl8nRx",1,0],[5,285.7,117],[-144.1,-473.6,0,0,0,0,1,1,1,1]],[7,"btn_yellow",6,[-116],[[8,1,0,-113,[9],10],[12,1,-115,[[13,"2457arSHXNKiqefBy7sYbr9","close",1]],-114]],[0,"bfwo64St5A+b8az31w5NTL",1,0],[5,285,117],[146.374,-473.309,0,0,0,0,1,1,1,1]],[7,"bgwindowtitle",6,[-118,-119],[[30,41,12,12,4,56,-117]],[0,"b3Ogg674JCI4FMFOEEGMcA",1,0],[5,602,95],[0,520.5,0,0,0,0,1,1,1,1]],[24,"view",[2],[[35,0,-120,[110]],[17,45,240,250,-121]],[0,"8dG5nZFxVOy7nrIPIUYelv",1,0],[5,597,860]],[2,"New Node0",3,[-122,-123,-124],[0,"f5B3OaK9lD2rrFu+NJka2n",1,0],[5,560,75],[0,262.5,0,0,0,0,1,1,1,1]],[2,"New Node1",3,[-125,-126,-127],[0,"31hF0vWtdOCJAY9h6ij7st",1,0],[5,560,75],[0,187.5,0,0,0,0,1,1,1,1]],[2,"New Node2",3,[-128,-129,-130],[0,"c2ipcXfapGf5erZH7nKv8w",1,0],[5,560,75],[0,112.5,0,0,0,0,1,1,1,1]],[2,"New Node3",3,[-131,-132,-133],[0,"2aBCY51e1GAYa9R4qOjsLZ",1,0],[5,560,75],[0,37.5,0,0,0,0,1,1,1,1]],[2,"New Node4",3,[-134,-135,-136],[0,"f0+4c6s3pMmL+oXJPYYuKh",1,0],[5,560,75],[0,-37.5,0,0,0,0,1,1,1,1]],[2,"New Node5",3,[-137,-138,-139],[0,"a3HtZsTtlIsqRMdxqzNGKw",1,0],[5,560,75],[0,-112.5,0,0,0,0,1,1,1,1]],[2,"New Node6",3,[-140,-141,-142],[0,"0fGEoFPNJNtZk0KpGgqQqs",1,0],[5,560,75],[0,-187.5,0,0,0,0,1,1,1,1]],[2,"New Node0",4,[-143,-144,-145],[0,"77f+GsnMNMH7bCJohKpWZv",1,0],[5,560,75],[0,262.5,0,0,0,0,1,1,1,1]],[2,"New Node1",4,[-146,-147,-148],[0,"dfrJDpGNNCYrIL0BOnXQNb",1,0],[5,560,75],[0,187.5,0,0,0,0,1,1,1,1]],[2,"New Node2",4,[-149,-150,-151],[0,"9bVr3oKsxIr4qDyTT3cu0X",1,0],[5,560,75],[0,112.5,0,0,0,0,1,1,1,1]],[2,"New Node3",4,[-152,-153,-154],[0,"45lqZM/wRH+KCd6+7KWqXo",1,0],[5,560,75],[0,37.5,0,0,0,0,1,1,1,1]],[2,"New Node4",4,[-155,-156,-157],[0,"45AVR2Ea9NU4/SfFTxrC1C",1,0],[5,560,75],[0,-37.5,0,0,0,0,1,1,1,1]],[2,"New Node5",4,[-158,-159,-160],[0,"6dpAJ2+uVLrpQP+5FO+5JS",1,0],[5,560,75],[0,-112.5,0,0,0,0,1,1,1,1]],[2,"New Node6",4,[-161,-162,-163],[0,"55h8DEWzhHnI0QUmoNhgyE",1,0],[5,560,75],[0,-187.5,0,0,0,0,1,1,1,1]],[2,"New Node0",5,[-164,-165,-166],[0,"begnD8QipHRYjMmLKJTzvP",1,0],[5,560,75],[0,262.5,0,0,0,0,1,1,1,1]],[2,"New Node1",5,[-167,-168,-169],[0,"1fREV5UkZM+4uPcC7LLxct",1,0],[5,560,75],[0,187.5,0,0,0,0,1,1,1,1]],[2,"New Node2",5,[-170,-171,-172],[0,"c8LiBR2m9LY4P70LfJtGJf",1,0],[5,560,75],[0,112.5,0,0,0,0,1,1,1,1]],[2,"New Node3",5,[-173,-174,-175],[0,"68lXGdnSdFDoR8DXhxTq+q",1,0],[5,560,75],[0,37.5,0,0,0,0,1,1,1,1]],[2,"New Node4",5,[-176,-177,-178],[0,"e7dPS1FvVKAb7VIWTVZ/L6",1,0],[5,560,75],[0,-37.5,0,0,0,0,1,1,1,1]],[2,"New Node5",5,[-179,-180,-181],[0,"04SjjUkpJESIPyGrymMwA+",1,0],[5,560,75],[0,-112.5,0,0,0,0,1,1,1,1]],[2,"New Node6",5,[-182,-183,-184],[0,"29xjC1Q/9FfKUS2rqCyqgT",1,0],[5,560,75],[0,-187.5,0,0,0,0,1,1,1,1]],[25,"mask",49,1,[[33,0,-185,[0],1],[31,45,-75,-75,100,100,-186]],[0,"986IzO+MFBLJAX+VipHKfQ",1,0],[4,4278190080],[5,750,1484]],[7,"btn_close",9,[-189],[[12,1,-188,[[13,"2457arSHXNKiqefBy7sYbr9","close",1]],-187]],[0,"d9rhRLB8xA5b+rM5iEysT6",1,0],[5,100,100],[252.591,0,0,0,0,0,1,1,1,1]],[26,"background",33,[[34,2,false,-190,[2],3]],[0,"00lom5hGtAHqyFwbiX0Mns",1,0],[5,34,35]],[27,"ScrollView",6,[10],[-191],[0,"a930emcKVNio+ACqIbiUqy",1,0],[5,597,860],[0,32,0,0,0,0,1,1,1,1]],[15,"lab_cardone",2,[[-192,[18,1,717.241,-193]],1,4],[0,"d3+3fnYxJHSK5TdS0iGfXQ",1,0],[4,4285420362],[5,300,50.4],[0,0,0.5],[-248,-742.441,0,0,0,0,1,1,1,1]],[15,"lab_cardthree",2,[[-194,[18,1,1413.8,-195]],1,4],[0,"24Al2Xv+NHbpoNtm3uHgWp",1,0],[4,4285420362],[5,300,50.4],[0,0,0.5],[-248,-1439,0,0,0,0,1,1,1,1]],[2,"New Node7",3,[-196,-197],[0,"0aiQJ0AlxMU5OpFIXCL8Wb",1,0],[5,560,75],[0,-262.5,0,0,0,0,1,1,1,1]],[2,"New Node7",4,[-198,-199],[0,"fbtR8dU8pJIr4Q0lHUW2jf",1,0],[5,560,75],[0,-262.5,0,0,0,0,1,1,1,1]],[2,"New Node7",5,[-200,-201],[0,"d8e44TPPFB9IfQPRB5NfYh",1,0],[5,560,75],[0,-262.5,0,0,0,0,1,1,1,1]],[28,"label",9,[-202],[0,"50AiLIr+pNvrSKn7gqAggw",1,0],[5,420,80]],[9,"统计信息",46,50,false,1,1,1,2,41,[4]],[16,"label",7,[-203],[0,"5224xtiaRI/bcGMq7SvjR9",1,0],[5,190,75],[0,4,0,0,0,0,1,1,1,1]],[9,"重置",42,45,false,1,1,1,2,43,[5]],[16,"label",8,[-204],[0,"ddbysNjMZDA6tRI8Vx0fUJ",1,0],[5,190,75],[0,4,0,0,0,0,1,1,1,1]],[9,"取消",42,45,false,1,1,1,2,45,[8]],[1,"lab_total",2,[-205],[0,"f4ApAvS3VPRpT3rWZn/1/6",1,0],[4,4285420362],[5,300,50.4],[0,0,0.5],[-248,-45,0,0,0,0,1,1,1,1]],[14,"Total Statistics",36,false,1,1,2,47,[11]],[14,"1 Card",36,false,1,1,2,36,[12]],[14,"3 Card",36,false,1,1,2,37,[13]],[3,"contentBg",2,[[8,1,0,-206,[14],15]],[0,"4eSnQhqiJAdYv5YxS2SBYr",1,0],[5,578.8,595.2],[0,-368.8,0,0,0,0,1,1,1,1]],[3,"contentBg2",2,[[8,1,0,-207,[16],17]],[0,"66k5GJurhEr5tVvS63kRCF",1,0],[5,578.8,595.2],[0,-1065.896,0,0,0,0,1,1,1,1]],[3,"contentBg3",2,[[8,1,0,-208,[18],19]],[0,"854OVEDGJKaINhGNcPfPMl",1,0],[5,578.8,595.2],[0,-1763,0,0,0,0,1,1,1,1]],[1,"label",11,[-209],[0,"89IXysd2JB2qkOvSjBMz6s",1,0],[4,4285420362],[5,350,52.92],[0,0,0.5],[-248,0,0,0,0,0,1,1,1,1]],[4,"游戏",32,35,false,1,1,2,54,[20]],[1,"label",11,[-210],[0,"745aKsAjRIBoDlUplHZ+Db",1,0],[4,4285420362],[5,200,50],[0,1,0.5],[249,0,0,0,0,0,1,1,1,1]],[9,"Label",32,35,false,1,2,1,2,56,[21]],[3,"cut_line",11,[[6,-211,[22],23]],[0,"22UZSqNCdGrbwRz4B6o5ac",1,0],[5,540,2],[0,-36,0,0,0,0,1,1,1,1]],[1,"label",12,[-212],[0,"16/wj8gU1NK4rQ/TL+X5zl",1,0],[4,4285420362],[5,350,52.92],[0,0,0.5],[-248,0,0,0,0,0,1,1,1,1]],[4,"胜利",32,35,false,1,1,2,59,[24]],[1,"label",12,[-213],[0,"b6laWD/+hMcrywPpL144oS",1,0],[4,4285420362],[5,83.58,44.1],[0,1,0.5],[249,0,0,0,0,0,1,1,1,1]],[5,"Label",32,35,1,1,1,61,[25]],[3,"cut_line",12,[[6,-214,[26],27]],[0,"e2PYZ32QRAgbOpU8g+wBU7",1,0],[5,540,2],[0,-36,0,0,0,0,1,1,1,1]],[1,"label",13,[-215],[0,"0e8a+mzWFEsZo1fuTjITlI",1,0],[4,4285420362],[5,350,52.92],[0,0,0.5],[-248,0,0,0,0,0,1,1,1,1]],[4,"连胜",32,35,false,1,1,2,64,[28]],[1,"label",13,[-216],[0,"97VBOGDf9EM6Z2MT28WeyH",1,0],[4,4285420362],[5,83.58,44.1],[0,1,0.5],[249,0,0,0,0,0,1,1,1,1]],[5,"Label",32,35,1,1,1,66,[29]],[3,"cut_line",13,[[6,-217,[30],31]],[0,"fbl+iwqS5PQaeKyrqP6Qmf",1,0],[5,540,2],[0,-36,0,0,0,0,1,1,1,1]],[1,"label",14,[-218],[0,"fb3oB/BaJPWJJa6FtO9+kX",1,0],[4,4285420362],[5,350,52.92],[0,0,0.5],[-248,0,0,0,0,0,1,1,1,1]],[4,"胜率",32,35,false,1,1,2,69,[32]],[1,"label",14,[-219],[0,"beYVTL+bhJO4hfeLxk898Y",1,0],[4,4285420362],[5,83.58,44.1],[0,1,0.5],[249,0,0,0,0,0,1,1,1,1]],[5,"Label",32,35,1,1,1,71,[33]],[3,"cut_line",14,[[6,-220,[34],35]],[0,"22mqoW13xOVZAc0OW52j0O",1,0],[5,540,2],[0,-36,0,0,0,0,1,1,1,1]],[1,"label",15,[-221],[0,"60Br6I4EBKBoEyct0w7Eeg",1,0],[4,4285420362],[5,350,52.92],[0,0,0.5],[-248,0,0,0,0,0,1,1,1,1]],[4,"最佳步数",32,35,false,1,1,2,74,[36]],[1,"label",15,[-222],[0,"33jQTwrWBGma/LUa7mrfD5",1,0],[4,4285420362],[5,83.58,44.1],[0,1,0.5],[249,0,0,0,0,0,1,1,1,1]],[5,"Label",32,35,1,1,1,76,[37]],[3,"cut_line",15,[[6,-223,[38],39]],[0,"50mz/BefxIiJ6s3cHRQ4yf",1,0],[5,540,2],[0,-36,0,0,0,0,1,1,1,1]],[1,"label",16,[-224],[0,"a2x1o6YtZLFrSSWdZ6Iswf",1,0],[4,4285420362],[5,350,52.92],[0,0,0.5],[-248,0,0,0,0,0,1,1,1,1]],[4,"最佳时间",32,35,false,1,1,2,79,[40]],[1,"label",16,[-225],[0,"10qK7X2ApLiKya58vWZYQO",1,0],[4,4285420362],[5,83.58,44.1],[0,1,0.5],[249,0,0,0,0,0,1,1,1,1]],[5,"Label",32,35,1,1,1,81,[41]],[3,"cut_line",16,[[6,-226,[42],43]],[0,"961hp3zXlCCJqNL56RYORr",1,0],[5,540,2],[0,-36,0,0,0,0,1,1,1,1]],[1,"label",17,[-227],[0,"a9j9J3dPlMn6dHImUxfJzr",1,0],[4,4285420362],[5,350,52.92],[0,0,0.5],[-248,0,0,0,0,0,1,1,1,1]],[4,"最佳分数",32,35,false,1,1,2,84,[44]],[1,"label",17,[-228],[0,"73xUtkW+5Fcbu+56KWt5pB",1,0],[4,4285420362],[5,83.58,44.1],[0,1,0.5],[249,0,0,0,0,0,1,1,1,1]],[5,"Label",32,35,1,1,1,86,[45]],[3,"cut_line",17,[[6,-229,[46],47]],[0,"faFAbsy5xDDaUDLuIX/ueT",1,0],[5,540,2],[0,-36,0,0,0,0,1,1,1,1]],[1,"label",38,[-230],[0,"dcfvT/ONZJVL1hieD2PXwx",1,0],[4,4285420362],[5,350,52.92],[0,0,0.5],[-248,0,0,0,0,0,1,1,1,1]],[4,"累计得分",32,35,false,1,1,2,89,[48]],[1,"label",38,[-231],[0,"72fvzeTDlFwpf1aLuA07V6",1,0],[4,4285420362],[5,83.58,44.1],[0,1,0.5],[249,0,0,0,0,0,1,1,1,1]],[5,"Label",32,35,1,1,1,91,[49]],[1,"label",18,[-232],[0,"c9TDqUxcVISKKhqGkvOC+g",1,0],[4,4285420362],[5,350,52.92],[0,0,0.5],[-248,0,0,0,0,0,1,1,1,1]],[4,"游戏",32,35,false,1,1,2,93,[50]],[1,"label",18,[-233],[0,"96INjoJz1ACqk9A6+PD/xI",1,0],[4,4285420362],[5,83.58,44.1],[0,1,0.5],[249,0,0,0,0,0,1,1,1,1]],[5,"Label",32,35,1,1,1,95,[51]],[3,"cut_line",18,[[6,-234,[52],53]],[0,"4eSRYasvNEvq3pB/8M7/Zi",1,0],[5,540,2],[0,-36,0,0,0,0,1,1,1,1]],[1,"label",19,[-235],[0,"53eqFybcFFs5+hUOgd0VFM",1,0],[4,4285420362],[5,350,52.92],[0,0,0.5],[-248,0,0,0,0,0,1,1,1,1]],[4,"胜利",32,35,false,1,1,2,98,[54]],[1,"label",19,[-236],[0,"35STWeU0pGuagWUpQIFghw",1,0],[4,4285420362],[5,83.58,44.1],[0,1,0.5],[249,0,0,0,0,0,1,1,1,1]],[5,"Label",32,35,1,1,1,100,[55]],[3,"cut_line",19,[[6,-237,[56],57]],[0,"28EnEtyq1NHKO+uqjluATa",1,0],[5,540,2],[0,-36,0,0,0,0,1,1,1,1]],[1,"label",20,[-238],[0,"a5qPyXBQZBUZgkGSzj3MYk",1,0],[4,4285420362],[5,350,52.92],[0,0,0.5],[-248,0,0,0,0,0,1,1,1,1]],[4,"连胜",32,35,false,1,1,2,103,[58]],[1,"label",20,[-239],[0,"08vS2Lnd1AcJs+4ugwoMlK",1,0],[4,4285420362],[5,83.58,44.1],[0,1,0.5],[249,0,0,0,0,0,1,1,1,1]],[5,"Label",32,35,1,1,1,105,[59]],[3,"cut_line",20,[[6,-240,[60],61]],[0,"3aOmMtWV9HeZKjsDrzC9Pb",1,0],[5,540,2],[0,-36,0,0,0,0,1,1,1,1]],[1,"label",21,[-241],[0,"5azLhAO3hDJYDNlEIWbZ6p",1,0],[4,4285420362],[5,350,52.92],[0,0,0.5],[-248,0,0,0,0,0,1,1,1,1]],[4,"胜率",32,35,false,1,1,2,108,[62]],[1,"label",21,[-242],[0,"55YlsNanBJE7m4ObLzh4xv",1,0],[4,4285420362],[5,83.58,44.1],[0,1,0.5],[249,0,0,0,0,0,1,1,1,1]],[5,"Label",32,35,1,1,1,110,[63]],[3,"cut_line",21,[[6,-243,[64],65]],[0,"0adflWkhJD34cj691lF/MO",1,0],[5,540,2],[0,-36,0,0,0,0,1,1,1,1]],[1,"label",22,[-244],[0,"e0cPrZHeNBH5xQnmh1Jrh7",1,0],[4,4285420362],[5,350,52.92],[0,0,0.5],[-248,0,0,0,0,0,1,1,1,1]],[4,"最佳步数",32,35,false,1,1,2,113,[66]],[1,"label",22,[-245],[0,"a4bFE1iGJNNbNeEo5osu7N",1,0],[4,4285420362],[5,83.58,44.1],[0,1,0.5],[249,0,0,0,0,0,1,1,1,1]],[5,"Label",32,35,1,1,1,115,[67]],[3,"cut_line",22,[[6,-246,[68],69]],[0,"2cjHbBTB9DApDCroDSF0Wj",1,0],[5,540,2],[0,-36,0,0,0,0,1,1,1,1]],[1,"label",23,[-247],[0,"e2ZRVbTLNLVpmSWX1vR142",1,0],[4,4285420362],[5,350,52.92],[0,0,0.5],[-248,0,0,0,0,0,1,1,1,1]],[4,"最佳时间",32,35,false,1,1,2,118,[70]],[1,"label",23,[-248],[0,"41pbQauLRPG72o53uMNhUT",1,0],[4,4285420362],[5,83.58,44.1],[0,1,0.5],[249,0,0,0,0,0,1,1,1,1]],[5,"Label",32,35,1,1,1,120,[71]],[3,"cut_line",23,[[6,-249,[72],73]],[0,"09xyL2JbNPpYQl6qxwC0L/",1,0],[5,540,2],[0,-36,0,0,0,0,1,1,1,1]],[1,"label",24,[-250],[0,"3bJUOIZ7ZMq6DNUEOFu+go",1,0],[4,4285420362],[5,350,52.92],[0,0,0.5],[-248,0,0,0,0,0,1,1,1,1]],[4,"最佳分数",32,35,false,1,1,2,123,[74]],[1,"label",24,[-251],[0,"b5rEr81clCMYn8xcvRzmC6",1,0],[4,4285420362],[5,83.58,44.1],[0,1,0.5],[249,0,0,0,0,0,1,1,1,1]],[5,"Label",32,35,1,1,1,125,[75]],[3,"cut_line",24,[[6,-252,[76],77]],[0,"7eArxZH6NORo5FX/RPetgc",1,0],[5,540,2],[0,-36,0,0,0,0,1,1,1,1]],[1,"label",39,[-253],[0,"7cKdyM9kNFZLLMakq9XQpd",1,0],[4,4285420362],[5,350,52.92],[0,0,0.5],[-248,0,0,0,0,0,1,1,1,1]],[4,"累计得分",32,35,false,1,1,2,128,[78]],[1,"label",39,[-254],[0,"a4SF8w+9NBV6p2KuNMEog5",1,0],[4,4285420362],[5,83.58,44.1],[0,1,0.5],[249,0,0,0,0,0,1,1,1,1]],[5,"Label",32,35,1,1,1,130,[79]],[1,"label",25,[-255],[0,"cfPjjiz2lBz42u4fAdzh2g",1,0],[4,4285420362],[5,350,52.92],[0,0,0.5],[-248,0,0,0,0,0,1,1,1,1]],[4,"游戏",32,35,false,1,1,2,132,[80]],[1,"label",25,[-256],[0,"0axAAyEulPx5Tdv3KGVR4K",1,0],[4,4285420362],[5,83.58,44.1],[0,1,0.5],[249,0,0,0,0,0,1,1,1,1]],[5,"Label",32,35,1,1,1,134,[81]],[3,"cut_line",25,[[6,-257,[82],83]],[0,"eeKmj+7MhBsZk1+w8tq+SB",1,0],[5,540,2],[0,-36,0,0,0,0,1,1,1,1]],[1,"label",26,[-258],[0,"b0YcDX2xFO6Ln8TERnwWoo",1,0],[4,4285420362],[5,350,52.92],[0,0,0.5],[-248,0,0,0,0,0,1,1,1,1]],[4,"胜利",32,35,false,1,1,2,137,[84]],[1,"label",26,[-259],[0,"9cPZ9/5AhHbq+R5c6LBepr",1,0],[4,4285420362],[5,83.58,44.1],[0,1,0.5],[249,0,0,0,0,0,1,1,1,1]],[5,"Label",32,35,1,1,1,139,[85]],[3,"cut_line",26,[[6,-260,[86],87]],[0,"c7I3x9mx1KNrxz06gtVx33",1,0],[5,540,2],[0,-36,0,0,0,0,1,1,1,1]],[1,"label",27,[-261],[0,"69ZdJx4wVNq7P5phiZvezg",1,0],[4,4285420362],[5,350,52.92],[0,0,0.5],[-248,0,0,0,0,0,1,1,1,1]],[4,"连胜",32,35,false,1,1,2,142,[88]],[1,"label",27,[-262],[0,"fe2rDmzwNLWKJwlR2LLtZT",1,0],[4,4285420362],[5,83.58,44.1],[0,1,0.5],[249,0,0,0,0,0,1,1,1,1]],[5,"Label",32,35,1,1,1,144,[89]],[3,"cut_line",27,[[6,-263,[90],91]],[0,"48SQmwmzdEHauQYv4KvFOi",1,0],[5,540,2],[0,-36,0,0,0,0,1,1,1,1]],[1,"label",28,[-264],[0,"2aZiRns/RIyrtxuL3eHmiC",1,0],[4,4285420362],[5,350,52.92],[0,0,0.5],[-248,0,0,0,0,0,1,1,1,1]],[4,"胜率",32,35,false,1,1,2,147,[92]],[1,"label",28,[-265],[0,"d679F45bdPw6K96UHqtcKf",1,0],[4,4285420362],[5,83.58,44.1],[0,1,0.5],[249,0,0,0,0,0,1,1,1,1]],[5,"Label",32,35,1,1,1,149,[93]],[3,"cut_line",28,[[6,-266,[94],95]],[0,"c6HPk87PZHB7d9OY/h0niA",1,0],[5,540,2],[0,-36,0,0,0,0,1,1,1,1]],[1,"label",29,[-267],[0,"5eUbCrS2NIPKLNZDQmM4NZ",1,0],[4,4285420362],[5,350,52.92],[0,0,0.5],[-248,0,0,0,0,0,1,1,1,1]],[4,"最佳步数",32,35,false,1,1,2,152,[96]],[1,"label",29,[-268],[0,"d0aC6V5URMWYCwdiljRgwh",1,0],[4,4285420362],[5,83.58,44.1],[0,1,0.5],[249,0,0,0,0,0,1,1,1,1]],[5,"Label",32,35,1,1,1,154,[97]],[3,"cut_line",29,[[6,-269,[98],99]],[0,"beITr0EgpKX4T/8lPh4FEG",1,0],[5,540,2],[0,-36,0,0,0,0,1,1,1,1]],[1,"label",30,[-270],[0,"a9DU06oh5CDrvI2mFsThdr",1,0],[4,4285420362],[5,350,52.92],[0,0,0.5],[-248,0,0,0,0,0,1,1,1,1]],[4,"最佳时间",32,35,false,1,1,2,157,[100]],[1,"label",30,[-271],[0,"8bIbLv0aNLc64vHtHD/O7h",1,0],[4,4285420362],[5,83.58,44.1],[0,1,0.5],[249,0,0,0,0,0,1,1,1,1]],[5,"Label",32,35,1,1,1,159,[101]],[3,"cut_line",30,[[6,-272,[102],103]],[0,"45LyWlx0JB7Zz1WrMcsn3U",1,0],[5,540,2],[0,-36,0,0,0,0,1,1,1,1]],[1,"label",31,[-273],[0,"5fnG/6LX5P66dfMAV9GnVb",1,0],[4,4285420362],[5,350,52.92],[0,0,0.5],[-248,0,0,0,0,0,1,1,1,1]],[4,"最佳分数",32,35,false,1,1,2,162,[104]],[1,"label",31,[-274],[0,"b8uvDvZ9hHRK9cEYHpvY9E",1,0],[4,4285420362],[5,83.58,44.1],[0,1,0.5],[249,0,0,0,0,0,1,1,1,1]],[5,"Label",32,35,1,1,1,164,[105]],[3,"cut_line",31,[[6,-275,[106],107]],[0,"ddOYkw9fpCO72HHn6HQUU7",1,0],[5,540,2],[0,-36,0,0,0,0,1,1,1,1]],[1,"label",40,[-276],[0,"d4aprARh5GQI2R+oDT/60b",1,0],[4,4285420362],[5,350,52.92],[0,0,0.5],[-248,0,0,0,0,0,1,1,1,1]],[4,"累计得分",32,35,false,1,1,2,167,[108]],[1,"label",40,[-277],[0,"62qaGh1O1J+Z1M2zfiW7dC",1,0],[4,4285420362],[5,83.58,44.1],[0,1,0.5],[249,0,0,0,0,0,1,1,1,1]],[5,"Label",32,35,1,1,1,169,[109]],[36,false,0.5,null,null,35,2],[37,1,[113,114]]],0,[0,5,1,0,6,171,0,-1,48,0,-2,49,0,-3,50,0,-1,135,0,-2,140,0,-3,145,0,-4,150,0,-5,155,0,-6,160,0,-7,165,0,-8,170,0,-1,133,0,-2,138,0,-3,143,0,-4,148,0,-5,153,0,-6,158,0,-7,163,0,-8,168,0,-1,96,0,-2,101,0,-3,106,0,-4,111,0,-5,116,0,-6,121,0,-7,126,0,-8,131,0,-1,94,0,-2,99,0,-3,104,0,-4,109,0,-5,114,0,-6,119,0,-7,124,0,-8,129,0,7,46,0,8,44,0,-1,57,0,-2,62,0,-3,67,0,-4,72,0,-5,77,0,-6,82,0,-7,87,0,-8,92,0,-1,55,0,-2,60,0,-3,65,0,-4,70,0,-5,75,0,-6,80,0,-7,85,0,-8,90,0,9,42,0,10,172,0,0,1,0,-2,172,0,0,1,0,0,1,0,-1,32,0,-2,6,0,-1,47,0,-2,36,0,-3,37,0,-4,51,0,-5,52,0,-6,53,0,-7,3,0,-8,4,0,-9,5,0,0,3,0,0,3,0,-1,11,0,-2,12,0,-3,13,0,-4,14,0,-5,15,0,-6,16,0,-7,17,0,-8,38,0,0,4,0,0,4,0,-1,18,0,-2,19,0,-3,20,0,-4,21,0,-5,22,0,-6,23,0,-7,24,0,-8,39,0,0,5,0,0,5,0,-1,25,0,-2,26,0,-3,27,0,-4,28,0,-5,29,0,-6,30,0,-7,31,0,-8,40,0,0,6,0,0,6,0,-1,9,0,-2,7,0,-3,8,0,-4,35,0,0,7,0,2,7,0,0,7,0,-1,43,0,0,8,0,2,8,0,0,8,0,-1,45,0,0,9,0,-1,33,0,-2,41,0,0,10,0,0,10,0,-1,54,0,-2,56,0,-3,58,0,-1,59,0,-2,61,0,-3,63,0,-1,64,0,-2,66,0,-3,68,0,-1,69,0,-2,71,0,-3,73,0,-1,74,0,-2,76,0,-3,78,0,-1,79,0,-2,81,0,-3,83,0,-1,84,0,-2,86,0,-3,88,0,-1,93,0,-2,95,0,-3,97,0,-1,98,0,-2,100,0,-3,102,0,-1,103,0,-2,105,0,-3,107,0,-1,108,0,-2,110,0,-3,112,0,-1,113,0,-2,115,0,-3,117,0,-1,118,0,-2,120,0,-3,122,0,-1,123,0,-2,125,0,-3,127,0,-1,132,0,-2,134,0,-3,136,0,-1,137,0,-2,139,0,-3,141,0,-1,142,0,-2,144,0,-3,146,0,-1,147,0,-2,149,0,-3,151,0,-1,152,0,-2,154,0,-3,156,0,-1,157,0,-2,159,0,-3,161,0,-1,162,0,-2,164,0,-3,166,0,0,32,0,0,32,0,2,34,0,0,33,0,-1,34,0,0,34,0,-1,171,0,-1,49,0,0,36,0,-1,50,0,0,37,0,-1,89,0,-2,91,0,-1,128,0,-2,130,0,-1,167,0,-2,169,0,-1,42,0,-1,44,0,-1,46,0,-1,48,0,0,51,0,0,52,0,0,53,0,-1,55,0,-1,57,0,0,58,0,-1,60,0,-1,62,0,0,63,0,-1,65,0,-1,67,0,0,68,0,-1,70,0,-1,72,0,0,73,0,-1,75,0,-1,77,0,0,78,0,-1,80,0,-1,82,0,0,83,0,-1,85,0,-1,87,0,0,88,0,-1,90,0,-1,92,0,-1,94,0,-1,96,0,0,97,0,-1,99,0,-1,101,0,0,102,0,-1,104,0,-1,106,0,0,107,0,-1,109,0,-1,111,0,0,112,0,-1,114,0,-1,116,0,0,117,0,-1,119,0,-1,121,0,0,122,0,-1,124,0,-1,126,0,0,127,0,-1,129,0,-1,131,0,-1,133,0,-1,135,0,0,136,0,-1,138,0,-1,140,0,0,141,0,-1,143,0,-1,145,0,0,146,0,-1,148,0,-1,150,0,0,151,0,-1,153,0,-1,155,0,0,156,0,-1,158,0,-1,160,0,0,161,0,-1,163,0,-1,165,0,0,166,0,-1,168,0,-1,170,0,11,1,2,3,10,10,3,35,277],[0,0,0,0,0,0,0,0,0,0,0,0,0,0,0,0,0,0,0,0,0,0,0,0,0,0,0,0,0,0,0,0,0,0,0,0,0,0,0,0,0,0,0,0,0,0,0,0,0,0,0,0,0,0,0,0,0,0,0,0,0,0,0,0,0,0,0,0,0,0,0,0,0,0,0,0,0,0,0,0,0,0,0,0,0,0,0,0,0,0,0,0,0,0,0,0,0,0,0,0,0,0,0,0,0,0,0,0,0,0,0,0,0,0,0,0,0],[-1,1,-1,1,-1,-1,-1,1,-1,-1,1,-1,-1,-1,-1,1,-1,1,-1,1,-1,-1,-1,1,-1,-1,-1,1,-1,-1,-1,1,-1,-1,-1,1,-1,-1,-1,1,-1,-1,-1,1,-1,-1,-1,1,-1,-1,-1,-1,-1,1,-1,-1,-1,1,-1,-1,-1,1,-1,-1,-1,1,-1,-1,-1,1,-1,-1,-1,1,-1,-1,-1,1,-1,-1,-1,-1,-1,1,-1,-1,-1,1,-1,-1,-1,1,-1,-1,-1,1,-1,-1,-1,1,-1,-1,-1,1,-1,-1,-1,1,-1,-1,-1,-1,1,-1,-2,12,13],[0,6,0,7,0,0,0,8,0,0,9,0,0,0,0,2,0,2,0,2,0,0,0,1,0,0,0,1,0,0,0,1,0,0,0,1,0,0,0,1,0,0,0,1,0,0,0,1,0,0,0,0,0,1,0,0,0,1,0,0,0,1,0,0,0,1,0,0,0,1,0,0,0,1,0,0,0,1,0,0,0,0,0,1,0,0,0,1,0,0,0,1,0,0,0,1,0,0,0,1,0,0,0,1,0,0,0,1,0,0,0,0,10,3,4,3,4]]]]